Workbook

Sheet 2026
A1: Annual Budget Dashboard - 2026
A3: Month | B3: Income | C3: Deductions | D3: Net Pay | E3: Debts & Needs | F3: Leftover Money
A4: January
A5: February
A6: March
A7: April
A8: May
A9: June
A10: July
A11: August
A12: September | B12: =September!E7 -> 16925 | C12: =September!E8 -> -1916.38 | D12: =September!E9 -> 15008.62 | E12: =September!E17+September!E26 -> 10214 | F12: =September!E35 -> 4794.62
A13: October | B13: =October!D7 -> 16925 | C13: =October!D8 -> -1916.38 | D13: =October!D9 -> 15008.62 | E13: =October!D16+October!D23 -> 0 | F13: =October!D26 -> 15008.62
A14: November | B14: =November!D7 -> 16925 | C14: =November!D8 -> -1916.38 | D14: =November!D9 -> 15008.62 | E14: =November!D16+November!D23 -> 0 | F14: =November!D26 -> 15008.62
A15: December | B15: =December!D7 -> 16925 | C15: =December!D8 -> -1916.38 | D15: =December!D9 -> 15008.62 | E15: =December!D16+December!D23 -> 0 | F15: =December!D26 -> 15008.62
A16: YTD Total | B16: =SUM(B12:B15) -> 67700 | C16: =SUM(C12:C15) -> -7665.52 | D16: =SUM(D12:D15) -> 60034.48 | E16: =SUM(E12:E15) -> 10214 | F16: =SUM(F12:F15) -> 49820.48

Sheet September
C1: September 2026 Budget
C3: Block 1: My Salary & Take-Home Pay
C4: Item / Name | E4: Amount (₱)
C5: SG2 Basic | E5: 14925
C6: PERA | E6: 2000
C7: Total Gross | E7: =SUM(E5:E6) -> 16925
C8: Standard Deductions | E8: -1916.38
C9: Net Take-Home | E9: =SUM(E7:E8) -> 15008.62
C11: Block 2: Bills & Debts to Pay (Babayaran sa Sahod)
C12: Item / Name | D12: Date | E12: Amount (₱) | F12: Status / Done?
C13: Utang kay Justine | E13: 400 | F13: Pending
C14: Utang kay Kenneth | E14: 300 | F14: Pending
C15: Utang kay Tatay | E15: 3300 | F15: Pending
C16: Additional Utang kay tatay | D16: Sept 30 | E16: 1000 | F16: Pending
C17: Total Debts | E17: =SUM(E13:E16) -> 5000
C19: Block 3: Needs & Expenses (List ng Need)
C20: Item / Name | D20: Date | E20: Amount (₱) | F20: Status / Done?
C21: Savings | E21: 2000 | F21: Pending
C22: Necessities | E22: 1500 | F22: Pending
C23: Gasoline | E23: 500 | F23: Pending
C24: Portable Vaccum | E24: 214 | F24: Pending
C25: Mini Washing | E25: 1000 | F25: Pending
C26: Total Needs | E26: =SUM(E21:E25) -> 5214
C28: Block 4: Gastos Before makuha ang sahod ko
C29: Item / Name | D29: Date | E29: Amount (₱) | F29: Status / Done?
C30: Tatak ng Notary | D30: 46296 | E30: 100 | F30: Pending
C31: Landbank Opening | D31: Sept 24 | E31: 100 | F31: Done
C32: Passport Photos & Laminate ID | D32: Sept 26 | E32: 100 | F32: Done
C34: Bottom Line Box
C35: Money Leftover / Savings | E35: =E9-E17-E26 -> 4794.62

Sheet October
B1: October 2026 Budget
B3: Block 1: My Salary & Take-Home Pay
B4: Item / Name | D4: Amount (₱)
B5: SG2 Basic | D5: 14925
B6: PERA | D6: 2000
B7: Total Gross | D7: =SUM(D5:D6) -> 16925
B8: Standard Deductions | D8: -1916.38
B9: Net Take-Home | D9: =SUM(D7:D8) -> 15008.62
B11: Block 2: Bills & Debts to Pay (Babayaran sa Sahod)
B12: Item / Name | C12: Date | D12: Amount (₱) | E12: Status / Done?
B16: Total Debts | D16: =SUM(D13:D15) -> 0
B18: Block 3: Needs & Expenses (List ng Need)
B19: Item / Name | C19: Date | D19: Amount (₱) | E19: Status / Done?
B20: Savings
B21: Necessities
B23: Total Needs | D23: =SUM(D20:D22) -> 0
B25: Bottom Line Box
B26: Money Leftover / Savings | D26: =D9-D16-D23 -> 15008.62

Sheet November
B1: November 2026 Budget
B3: Block 1: My Salary & Take-Home Pay
B4: Item / Name | D4: Amount (₱)
B5: SG2 Basic | D5: 14925
B6: PERA | D6: 2000
B7: Total Gross | D7: =SUM(D5:D6) -> 16925
B8: Standard Deductions | D8: -1916.38
B9: Net Take-Home | D9: =SUM(D7:D8) -> 15008.62
B11: Block 2: Bills & Debts to Pay (Babayaran sa Sahod)
B12: Item / Name | C12: Date | D12: Amount (₱) | E12: Status / Done?
B16: Total Debts | D16: =SUM(D13:D15) -> 0
B18: Block 3: Needs & Expenses (List ng Need)
B19: Item / Name | C19: Date | D19: Amount (₱) | E19: Status / Done?
B20: Savings | E20: Pending
B21: Necessities | E21: Pending
B23: Total Needs | D23: =SUM(D20:D22) -> 0
B25: Bottom Line Box
B26: Money Leftover / Savings | D26: =D9-D16-D23 -> 15008.62

Sheet December
B1: December 2026 Budget
B3: Block 1: My Salary & Take-Home Pay
B4: Item / Name | D4: Amount (₱)
B5: SG2 Basic | D5: 14925
B6: PERA | D6: 2000
B7: Total Gross | D7: =SUM(D5:D6) -> 16925
B8: Standard Deductions | D8: -1916.38
B9: Net Take-Home | D9: =SUM(D7:D8) -> 15008.62
B11: Block 2: Bills & Debts to Pay (Babayaran sa Sahod)
B12: Item / Name | C12: Date | D12: Amount (₱) | E12: Status / Done?
B16: Total Debts | D16: =SUM(D13:D15) -> 0
B18: Block 3: Needs & Expenses (List ng Need)
B19: Item / Name | C19: Date | D19: Amount (₱) | E19: Status / Done?
B20: Savings | E20: Pending
B21: Necessities | E21: Pending
B23: Total Needs | D23: =SUM(D20:D22) -> 0
B25: Bottom Line Box
B26: Money Leftover / Savings | D26: =D9-D16-D23 -> 15008.62
